vlem/__init__.py
vlem/__main__.py
vlem/cli.py
vlem/constants.py
vlem/docker_client.py
vlem/error.py
vlem/handler.py
vlem/helper.py
vlem/utils.py
vlem-0.1.0.dist-info/LICENSE
vlem-0.1.0.dist-info/METADATA
vlem-0.1.0.dist-info/WHEEL
vlem-0.1.0.dist-info/entry_points.txt
vlem-0.1.0.dist-info/RECORD
